cadmium_django/__init__.py
cadmium_django/middleware.py
cadmium_django/signals.py
cadmium_django/utils.py
cadmium_django_sdk-1.2.1.dist-info/METADATA
cadmium_django_sdk-1.2.1.dist-info/WHEEL
cadmium_django_sdk-1.2.1.dist-info/top_level.txt
cadmium_django_sdk-1.2.1.dist-info/RECORD
