Metadata-Version: 2.1
Name: cadmium-django-sdk
Version: 1.2.1
Summary: Cadmium SDK for capturing and sending Django errors.
Home-page: https://github.com/bannawandoor27/cadmium-django-sdk
Author: bannawandoor
Author-email: connect@hasanulbanna.in
License: UNKNOWN
Platform: UNKNOWN
Classifier: Programming Language :: Python :: 3
Classifier: Framework :: Django
Requires-Dist: requests (>=2.0.0)
Requires-Dist: Django (>=3.0)
